CHANGES.txt
DEPENDENCES.txt
README.txt
setup.py
src/ng/__init__.py
src/ng.app.rubricator.egg-info/PKG-INFO
src/ng.app.rubricator.egg-info/SOURCES.txt
src/ng.app.rubricator.egg-info/dependency_links.txt
src/ng.app.rubricator.egg-info/namespace_packages.txt
src/ng.app.rubricator.egg-info/not-zip-safe
src/ng.app.rubricator.egg-info/requires.txt
src/ng.app.rubricator.egg-info/top_level.txt
src/ng/app/__init__.py
src/ng/app/rubricator/__init__.py
src/ng/app/rubricator/configure.zcml
src/ng/app/rubricator/interfaces.py
src/ng/app/rubricator/ng.app.rubricator.txt
src/ng/app/rubricator/etc/ng,app.rubricator-configure.zcml
src/ng/app/rubricator/filterannotation/__init__.py
src/ng/app/rubricator/filterannotation/configure.zcml
src/ng/app/rubricator/filterannotation/filterannotableadapter.py
src/ng/app/rubricator/filterannotation/filterannotation.py
src/ng/app/rubricator/filterannotation/interfaces.py
src/ng/app/rubricator/filterannotation/browser/__init__.py
src/ng/app/rubricator/filterannotation/browser/configure.zcml
src/ng/app/rubricator/filterannotation/browser/filterannotableedit.py
src/ng/app/rubricator/filterannotation/demo/__init__.py
src/ng/app/rubricator/filterannotation/demo/configure.zcml
src/ng/app/rubricator/newsref/__init__.py
src/ng/app/rubricator/newsref/configure.zcml
src/ng/app/rubricator/newsref/newshandler/__init__.py
src/ng/app/rubricator/newsref/newshandler/configure.zcml
src/ng/app/rubricator/newsref/newshandler/newshandler.py
src/ng/app/rubricator/newsref/newshandler/newshandler.txt
src/ng/app/rubricator/newsref/newsref/__init__.py
src/ng/app/rubricator/newsref/newsref/configure.zcml
src/ng/app/rubricator/newsref/newsref/interfaces.py
src/ng/app/rubricator/newsref/newsref/newsref.py
src/ng/app/rubricator/newsref/newsref/newsref.txt
src/ng/app/rubricator/newsref/newsref/browser/__init__.py
src/ng/app/rubricator/newsref/newsref/browser/configure.zcml
src/ng/app/rubricator/newsref/newsref2newsadapter/__init__.py
src/ng/app/rubricator/newsref/newsref2newsadapter/configure.zcml
src/ng/app/rubricator/newsref/newsref2newsadapter/newsref2newsadapter.py
src/ng/app/rubricator/newsref/newsref2newsadapter/newsref2newsadapter.txt
src/ng/app/rubricator/newsref/newsrefbackreference/__init__.py
src/ng/app/rubricator/newsref/newsrefbackreference/configure.zcml
